pass2csv.py
pass2csv-1.2.0.dist-info/LICENSE
pass2csv-1.2.0.dist-info/METADATA
pass2csv-1.2.0.dist-info/WHEEL
pass2csv-1.2.0.dist-info/entry_points.txt
pass2csv-1.2.0.dist-info/top_level.txt
pass2csv-1.2.0.dist-info/RECORD
