Metadata-Version: 2.2
Name: pass2csv
Version: 1.2.0
Summary: Export pass(1), "the standard unix password manager", to CSV
Maintainer-email: Rupus Reinefjord <rupus@reinefjord.net>
Project-URL: Homepage, https://codeberg.org/svartstare/pass2csv
Project-URL: Changelog, https://codeberg.org/svartstare/pass2csv/src/branch/master/NEWS
Keywords: csv,export,pass2csv
Classifier: Development Status :: 5 - Production/Stable
Classifier: Environment :: Console
Classifier: Intended Audience :: End Users/Desktop
Classifier: License :: OSI Approved :: MIT License
Classifier: Programming Language :: Python
Classifier: Programming Language :: Python :: 3
Classifier: Programming Language :: Python :: 3.6
Classifier: Topic :: Utilities
Requires-Python: >=3.6
License-File: LICENSE
Requires-Dist: python-gnupg
